<Document doc_name="62405_Sub-prime_lenders_send_jitters_through_global_markets">
<token t_id="1" sentence="0" number="0">Sub-prime</token>
<token t_id="2" sentence="0" number="1">lenders</token>
<token t_id="3" sentence="0" number="2">send</token>
<token t_id="4" sentence="0" number="3">jitters</token>
<token t_id="5" sentence="0" number="4">through</token>
<token t_id="6" sentence="0" number="5">global</token>
<token t_id="7" sentence="0" number="6">markets</token>
<token t_id="8" sentence="1" number="7">March</token>
<token t_id="9" sentence="1" number="8">13</token>
<token t_id="10" sentence="1" number="9">,</token>
<token t_id="11" sentence="1" number="10">2007</token>
<token t_id="12" sentence="2" number="11">Just</token>
<token t_id="13" sentence="2" number="12">two</token>
<token t_id="14" sentence="2" number="13">weeks</token>
<token t_id="15" sentence="2" number="14">after</token>
<token t_id="16" sentence="2" number="15">China</token>
<token t_id="17" sentence="2" number="16">sent</token>
<token t_id="18" sentence="2" number="17">global</token>
<token t_id="19" sentence="2" number="18">markets</token>
<token t_id="20" sentence="2" number="19">into</token>
<token t_id="21" sentence="2" number="20">a</token>
<token t_id="22" sentence="2" number="21">tumble</token>
<token t_id="23" sentence="2" number="22">,</token>
<token t_id="24" sentence="2" number="23">growing</token>
<token t_id="25" sentence="2" number="24">worries</token>
<token t_id="26" sentence="2" number="25">about</token>
<token t_id="27" sentence="2" number="26">sub-prime</token>
<token t_id="28" sentence="2" number="27">mortgage</token>
<token t_id="29" sentence="2" number="28">lenders</token>
<token t_id="30" sentence="2" number="29">in</token>
<token t_id="31" sentence="2" number="30">the</token>
<token t_id="32" sentence="2" number="31">United</token>
<token t_id="33" sentence="2" number="32">States</token>
<token t_id="34" sentence="2" number="33">are</token>
<token t_id="35" sentence="2" number="34">sending</token>
<token t_id="36" sentence="2" number="35">jitters</token>
<token t_id="37" sentence="2" number="36">through</token>
<token t_id="38" sentence="2" number="37">stock</token>
<token t_id="39" sentence="2" number="38">exchanges</token>
<token t_id="40" sentence="2" number="39">around</token>
<token t_id="41" sentence="2" number="40">the</token>
<token t_id="42" sentence="2" number="41">globe</token>
<token t_id="43" sentence="2" number="42">.</token>
<token t_id="44" sentence="3" number="43">The</token>
<token t_id="45" sentence="3" number="44">three</token>
<token t_id="46" sentence="3" number="45">major</token>
<token t_id="47" sentence="3" number="46">US</token>
<token t_id="48" sentence="3" number="47">stock</token>
<token t_id="49" sentence="3" number="48">market</token>
<token t_id="50" sentence="3" number="49">indices</token>
<token t_id="51" sentence="3" number="50">each</token>
<token t_id="52" sentence="3" number="51">fell</token>
<token t_id="53" sentence="3" number="52">two</token>
<token t_id="54" sentence="3" number="53">percent</token>
<token t_id="55" sentence="3" number="54">from</token>
<token t_id="56" sentence="3" number="55">Monday</token>
<token t_id="57" sentence="3" number="56">'s</token>
<token t_id="58" sentence="3" number="57">closing</token>
<token t_id="59" sentence="3" number="58">price</token>
<token t_id="60" sentence="3" number="59">,</token>
<token t_id="61" sentence="3" number="60">marking</token>
<token t_id="62" sentence="3" number="61">the</token>
<token t_id="63" sentence="3" number="62">second-biggest</token>
<token t_id="64" sentence="3" number="63">loss</token>
<token t_id="65" sentence="3" number="64">of</token>
<token t_id="66" sentence="3" number="65">2007</token>
<token t_id="67" sentence="3" number="66">.</token>
<token t_id="68" sentence="4" number="67">London</token>
<token t_id="69" sentence="4" number="68">'s</token>
<token t_id="70" sentence="4" number="69">FTSE</token>
<token t_id="71" sentence="4" number="70">100</token>
<token t_id="72" sentence="4" number="71">,</token>
<token t_id="73" sentence="4" number="72">Paris</token>
<token t_id="74" sentence="4" number="73">'</token>
<token t_id="75" sentence="4" number="74">CAC</token>
<token t_id="76" sentence="4" number="75">40</token>
<token t_id="77" sentence="4" number="76">and</token>
<token t_id="78" sentence="4" number="77">Frankfurt</token>
<token t_id="79" sentence="4" number="78">'s</token>
<token t_id="80" sentence="4" number="79">DAX</token>
<token t_id="81" sentence="4" number="80">30</token>
<token t_id="82" sentence="4" number="81">indices</token>
<token t_id="83" sentence="4" number="82">each</token>
<token t_id="84" sentence="4" number="83">closed</token>
<token t_id="85" sentence="4" number="84">down</token>
<token t_id="86" sentence="4" number="85">more</token>
<token t_id="87" sentence="4" number="86">than</token>
<token t_id="88" sentence="4" number="87">1</token>
<token t_id="89" sentence="4" number="88">percent</token>
<token t_id="90" sentence="4" number="89">.</token>
<token t_id="91" sentence="5" number="90">As</token>
<token t_id="92" sentence="5" number="91">the</token>
<token t_id="93" sentence="5" number="92">Mortgage</token>
<token t_id="94" sentence="5" number="93">Bankers</token>
<token t_id="95" sentence="5" number="94">Association</token>
<token t_id="96" sentence="5" number="95">reported</token>
<token t_id="97" sentence="5" number="96">that</token>
<token t_id="98" sentence="5" number="97">late</token>
<token t_id="99" sentence="5" number="98">payments</token>
<token t_id="100" sentence="5" number="99">on</token>
<token t_id="101" sentence="5" number="100">mortgages</token>
<token t_id="102" sentence="5" number="101">and</token>
<token t_id="103" sentence="5" number="102">home</token>
<token t_id="104" sentence="5" number="103">foreclosures</token>
<token t_id="105" sentence="5" number="104">in</token>
<token t_id="106" sentence="5" number="105">the</token>
<token t_id="107" sentence="5" number="106">US</token>
<token t_id="108" sentence="5" number="107">homes</token>
<token t_id="109" sentence="5" number="108">rose</token>
<token t_id="110" sentence="5" number="109">in</token>
<token t_id="111" sentence="5" number="110">the</token>
<token t_id="112" sentence="5" number="111">fourth</token>
<token t_id="113" sentence="5" number="112">quarter</token>
<token t_id="114" sentence="5" number="113">to</token>
<token t_id="115" sentence="5" number="114">their</token>
<token t_id="116" sentence="5" number="115">highest</token>
<token t_id="117" sentence="5" number="116">level</token>
<token t_id="118" sentence="5" number="117">in</token>
<token t_id="119" sentence="5" number="118">years</token>
<token t_id="120" sentence="5" number="119">,</token>
<token t_id="121" sentence="5" number="120">investors</token>
<token t_id="122" sentence="5" number="121">are</token>
<token t_id="123" sentence="5" number="122">concerned</token>
<token t_id="124" sentence="5" number="123">that</token>
<token t_id="125" sentence="5" number="124">not</token>
<token t_id="126" sentence="5" number="125">only</token>
<token t_id="127" sentence="5" number="126">US</token>
<token t_id="128" sentence="5" number="127">banks</token>
<token t_id="129" sentence="5" number="128">but</token>
<token t_id="130" sentence="5" number="129">also</token>
<token t_id="131" sentence="5" number="130">multi-national</token>
<token t_id="132" sentence="5" number="131">banks</token>
<token t_id="133" sentence="5" number="132">around</token>
<token t_id="134" sentence="5" number="133">the</token>
<token t_id="135" sentence="5" number="134">globe</token>
<token t_id="136" sentence="5" number="135">could</token>
<token t_id="137" sentence="5" number="136">have</token>
<token t_id="138" sentence="5" number="137">exposure</token>
<token t_id="139" sentence="5" number="138">.</token>
<token t_id="140" sentence="6" number="139">More</token>
<token t_id="141" sentence="6" number="140">than</token>
<token t_id="142" sentence="6" number="141">two</token>
<token t_id="143" sentence="6" number="142">dozen</token>
<token t_id="144" sentence="6" number="143">sub-prime</token>
<token t_id="145" sentence="6" number="144">lenders</token>
<token t_id="146" sentence="6" number="145">have</token>
<token t_id="147" sentence="6" number="146">closed</token>
<token t_id="148" sentence="6" number="147">or</token>
<token t_id="149" sentence="6" number="148">sold</token>
<token t_id="150" sentence="6" number="149">operations</token>
<token t_id="151" sentence="6" number="150">as</token>
<token t_id="152" sentence="6" number="151">defaults</token>
<token t_id="153" sentence="6" number="152">on</token>
<token t_id="154" sentence="6" number="153">those</token>
<token t_id="155" sentence="6" number="154">mortgages</token>
<token t_id="156" sentence="6" number="155">have</token>
<token t_id="157" sentence="6" number="156">risen</token>
<token t_id="158" sentence="6" number="157">.</token>
<token t_id="159" sentence="7" number="158">``</token>
<token t_id="160" sentence="7" number="159">The</token>
<token t_id="161" sentence="7" number="160">delinquencies</token>
<token t_id="162" sentence="7" number="161">and</token>
<token t_id="163" sentence="7" number="162">defaults</token>
<token t_id="164" sentence="7" number="163">have</token>
<token t_id="165" sentence="7" number="164">started</token>
<token t_id="166" sentence="7" number="165">to</token>
<token t_id="167" sentence="7" number="166">soar</token>
<token t_id="168" sentence="7" number="167">,</token>
<token t_id="169" sentence="7" number="168">''</token>
<token t_id="170" sentence="7" number="169">said</token>
<token t_id="171" sentence="7" number="170">Nicolas</token>
<token t_id="172" sentence="7" number="171">Retsinas</token>
<token t_id="173" sentence="7" number="172">,</token>
<token t_id="174" sentence="7" number="173">director</token>
<token t_id="175" sentence="7" number="174">of</token>
<token t_id="176" sentence="7" number="175">Housing</token>
<token t_id="177" sentence="7" number="176">Studies</token>
<token t_id="178" sentence="7" number="177">at</token>
<token t_id="179" sentence="7" number="178">Harvard</token>
<token t_id="180" sentence="7" number="179">University</token>
<token t_id="181" sentence="7" number="180">.</token>
<token t_id="182" sentence="8" number="181">``</token>
<token t_id="183" sentence="8" number="182">A</token>
<token t_id="184" sentence="8" number="183">lot</token>
<token t_id="185" sentence="8" number="184">of</token>
<token t_id="186" sentence="8" number="185">these</token>
<token t_id="187" sentence="8" number="186">lenders</token>
<token t_id="188" sentence="8" number="187">started</token>
<token t_id="189" sentence="8" number="188">to</token>
<token t_id="190" sentence="8" number="189">make</token>
<token t_id="191" sentence="8" number="190">loans</token>
<token t_id="192" sentence="8" number="191">and</token>
<token t_id="193" sentence="8" number="192">lost</token>
<token t_id="194" sentence="8" number="193">track</token>
<token t_id="195" sentence="8" number="194">of</token>
<token t_id="196" sentence="8" number="195">some</token>
<token t_id="197" sentence="8" number="196">of</token>
<token t_id="198" sentence="8" number="197">the</token>
<token t_id="199" sentence="8" number="198">fundamentals</token>
<token t_id="200" sentence="8" number="199">.</token>
<token t_id="201" sentence="8" number="200">''</token>
<token t_id="202" sentence="9" number="201">New</token>
<token t_id="203" sentence="9" number="202">Century</token>
<token t_id="204" sentence="9" number="203">Financial</token>
<token t_id="205" sentence="9" number="204">Corporation</token>
<token t_id="206" sentence="9" number="205">,</token>
<token t_id="207" sentence="9" number="206">the</token>
<token t_id="208" sentence="9" number="207">second</token>
<token t_id="209" sentence="9" number="208">largest</token>
<token t_id="210" sentence="9" number="209">sub-prime</token>
<token t_id="211" sentence="9" number="210">lender</token>
<token t_id="212" sentence="9" number="211">in</token>
<token t_id="213" sentence="9" number="212">the</token>
<token t_id="214" sentence="9" number="213">US</token>
<token t_id="215" sentence="9" number="214">,</token>
<token t_id="216" sentence="9" number="215">has</token>
<token t_id="217" sentence="9" number="216">recently</token>
<token t_id="218" sentence="9" number="217">revealed</token>
<token t_id="219" sentence="9" number="218">that</token>
<token t_id="220" sentence="9" number="219">its</token>
<token t_id="221" sentence="9" number="220">creditors</token>
<token t_id="222" sentence="9" number="221">were</token>
<token t_id="223" sentence="9" number="222">no</token>
<token t_id="224" sentence="9" number="223">longer</token>
<token t_id="225" sentence="9" number="224">providing</token>
<token t_id="226" sentence="9" number="225">funds</token>
<token t_id="227" sentence="9" number="226">and</token>
<token t_id="228" sentence="9" number="227">,</token>
<token t_id="229" sentence="9" number="228">further</token>
<token t_id="230" sentence="9" number="229">,</token>
<token t_id="231" sentence="9" number="230">it</token>
<token t_id="232" sentence="9" number="231">has</token>
<token t_id="233" sentence="9" number="232">become</token>
<token t_id="234" sentence="9" number="233">subject</token>
<token t_id="235" sentence="9" number="234">of</token>
<token t_id="236" sentence="9" number="235">an</token>
<token t_id="237" sentence="9" number="236">SEC</token>
<token t_id="238" sentence="9" number="237">investigation</token>
<token t_id="239" sentence="9" number="238">.</token>
<token t_id="240" sentence="10" number="239">The</token>
<token t_id="241" sentence="10" number="240">New</token>
<token t_id="242" sentence="10" number="241">York</token>
<token t_id="243" sentence="10" number="242">Stock</token>
<token t_id="244" sentence="10" number="243">Exchange</token>
<token t_id="245" sentence="10" number="244">has</token>
<token t_id="246" sentence="10" number="245">said</token>
<token t_id="247" sentence="10" number="246">it</token>
<token t_id="248" sentence="10" number="247">will</token>
<token t_id="249" sentence="10" number="248">delist</token>
<token t_id="250" sentence="10" number="249">New</token>
<token t_id="251" sentence="10" number="250">Century</token>
<token t_id="252" sentence="10" number="251">.</token>
<token t_id="253" sentence="11" number="252">Accredited</token>
<token t_id="254" sentence="11" number="253">Home</token>
<token t_id="255" sentence="11" number="254">Loan</token>
<token t_id="256" sentence="11" number="255">Lending</token>
<token t_id="257" sentence="11" number="256">,</token>
<token t_id="258" sentence="11" number="257">another</token>
<token t_id="259" sentence="11" number="258">major</token>
<token t_id="260" sentence="11" number="259">sub-prime</token>
<token t_id="261" sentence="11" number="260">mortgage</token>
<token t_id="262" sentence="11" number="261">specialist</token>
<token t_id="263" sentence="11" number="262">,</token>
<token t_id="264" sentence="11" number="263">said</token>
<token t_id="265" sentence="11" number="264">it</token>
<token t_id="266" sentence="11" number="265">was</token>
<token t_id="267" sentence="11" number="266">seeking</token>
<token t_id="268" sentence="11" number="267">fresh</token>
<token t_id="269" sentence="11" number="268">capital</token>
<token t_id="270" sentence="11" number="269">and</token>
<token t_id="271" sentence="11" number="270">waivers</token>
<token t_id="272" sentence="11" number="271">on</token>
<token t_id="273" sentence="11" number="272">its</token>
<token t_id="274" sentence="11" number="273">lending</token>
<token t_id="275" sentence="11" number="274">covenants</token>
<token t_id="276" sentence="11" number="275">.</token>
<token t_id="277" sentence="12" number="276">Sub-prime</token>
<token t_id="278" sentence="12" number="277">lenders</token>
<token t_id="279" sentence="12" number="278">provide</token>
<token t_id="280" sentence="12" number="279">mortgages</token>
<token t_id="281" sentence="12" number="280">to</token>
<token t_id="282" sentence="12" number="281">people</token>
<token t_id="283" sentence="12" number="282">who</token>
<token t_id="284" sentence="12" number="283">do</token>
<token t_id="285" sentence="12" number="284">not</token>
<token t_id="286" sentence="12" number="285">qualify</token>
<token t_id="287" sentence="12" number="286">for</token>
<token t_id="288" sentence="12" number="287">loans</token>
<token t_id="289" sentence="12" number="288">from</token>
<token t_id="290" sentence="12" number="289">mainstream</token>
<token t_id="291" sentence="12" number="290">lenders</token>
<token t_id="292" sentence="12" number="291">,</token>
<token t_id="293" sentence="12" number="292">typically</token>
<token t_id="294" sentence="12" number="293">due</token>
<token t_id="295" sentence="12" number="294">to</token>
<token t_id="296" sentence="12" number="295">their</token>
<token t_id="297" sentence="12" number="296">credit</token>
<token t_id="298" sentence="12" number="297">histories</token>
<token t_id="299" sentence="12" number="298">.</token>
<token t_id="300" sentence="13" number="299">The</token>
<token t_id="301" sentence="13" number="300">lenders</token>
<token t_id="302" sentence="13" number="301">then</token>
<token t_id="303" sentence="13" number="302">bundle</token>
<token t_id="304" sentence="13" number="303">these</token>
<token t_id="305" sentence="13" number="304">mortgages</token>
<token t_id="306" sentence="13" number="305">as</token>
<token t_id="307" sentence="13" number="306">collateral</token>
<token t_id="308" sentence="13" number="307">for</token>
<token t_id="309" sentence="13" number="308">loans</token>
<token t_id="310" sentence="13" number="309">that</token>
<token t_id="311" sentence="13" number="310">they</token>
<token t_id="312" sentence="13" number="311">obtain</token>
<token t_id="313" sentence="13" number="312">from</token>
<token t_id="314" sentence="13" number="313">other</token>
<token t_id="315" sentence="13" number="314">financing</token>
<token t_id="316" sentence="13" number="315">firms</token>
<token t_id="317" sentence="13" number="316">,</token>
<token t_id="318" sentence="13" number="317">such</token>
<token t_id="319" sentence="13" number="318">as</token>
<token t_id="320" sentence="13" number="319">GMAC</token>
<token t_id="321" sentence="13" number="320">.</token>
<token t_id="322" sentence="14" number="321">Such</token>
<token t_id="323" sentence="14" number="322">firms</token>
<token t_id="324" sentence="14" number="323">can</token>
<token t_id="325" sentence="14" number="324">then</token>
<token t_id="326" sentence="14" number="325">repackage</token>
<token t_id="327" sentence="14" number="326">these</token>
<token t_id="328" sentence="14" number="327">loans</token>
<token t_id="329" sentence="14" number="328">and</token>
<token t_id="330" sentence="14" number="329">sell</token>
<token t_id="331" sentence="14" number="330">them</token>
<token t_id="332" sentence="14" number="331">as</token>
<token t_id="333" sentence="14" number="332">mortgage-backed</token>
<token t_id="334" sentence="14" number="333">securities</token>
<token t_id="335" sentence="14" number="334">.</token>
<token t_id="336" sentence="15" number="335">These</token>
<token t_id="337" sentence="15" number="336">securities</token>
<token t_id="338" sentence="15" number="337">may</token>
<token t_id="339" sentence="15" number="338">end</token>
<token t_id="340" sentence="15" number="339">up</token>
<token t_id="341" sentence="15" number="340">in</token>
<token t_id="342" sentence="15" number="341">the</token>
<token t_id="343" sentence="15" number="342">hands</token>
<token t_id="344" sentence="15" number="343">of</token>
<token t_id="345" sentence="15" number="344">major</token>
<token t_id="346" sentence="15" number="345">multi-national</token>
<token t_id="347" sentence="15" number="346">banks</token>
<token t_id="348" sentence="15" number="347">such</token>
<token t_id="349" sentence="15" number="348">as</token>
<token t_id="350" sentence="15" number="349">Citibank</token>
<token t_id="351" sentence="15" number="350">,</token>
<token t_id="352" sentence="15" number="351">HSBC</token>
<token t_id="353" sentence="15" number="352">,</token>
<token t_id="354" sentence="15" number="353">and</token>
<token t_id="355" sentence="15" number="354">Commerzbank</token>
<token t_id="356" sentence="15" number="355">.</token>
<token t_id="357" sentence="16" number="356">Each</token>
<token t_id="358" sentence="16" number="357">level</token>
<token t_id="359" sentence="16" number="358">of</token>
<token t_id="360" sentence="16" number="359">lending</token>
<token t_id="361" sentence="16" number="360">assumes</token>
<token t_id="362" sentence="16" number="361">a</token>
<token t_id="363" sentence="16" number="362">level</token>
<token t_id="364" sentence="16" number="363">of</token>
<token t_id="365" sentence="16" number="364">financial</token>
<token t_id="366" sentence="16" number="365">risk</token>
<token t_id="367" sentence="16" number="366">,</token>
<token t_id="368" sentence="16" number="367">but</token>
<token t_id="369" sentence="16" number="368">trouble</token>
<token t_id="370" sentence="16" number="369">can</token>
<token t_id="371" sentence="16" number="370">arise</token>
<token t_id="372" sentence="16" number="371">when</token>
<token t_id="373" sentence="16" number="372">the</token>
<token t_id="374" sentence="16" number="373">risk</token>
<token t_id="375" sentence="16" number="374">tolerances</token>
<token t_id="376" sentence="16" number="375">are</token>
<token t_id="377" sentence="16" number="376">exceeded</token>
<token t_id="378" sentence="16" number="377">.</token>
<token t_id="379" sentence="17" number="378">If</token>
<token t_id="380" sentence="17" number="379">too</token>
<token t_id="381" sentence="17" number="380">many</token>
<token t_id="382" sentence="17" number="381">homeowners</token>
<token t_id="383" sentence="17" number="382">default</token>
<token t_id="384" sentence="17" number="383">on</token>
<token t_id="385" sentence="17" number="384">their</token>
<token t_id="386" sentence="17" number="385">mortgages</token>
<token t_id="387" sentence="17" number="386">,</token>
<token t_id="388" sentence="17" number="387">the</token>
<token t_id="389" sentence="17" number="388">sub-prime</token>
<token t_id="390" sentence="17" number="389">lender</token>
<token t_id="391" sentence="17" number="390">can</token>
<token t_id="392" sentence="17" number="391">end</token>
<token t_id="393" sentence="17" number="392">up</token>
<token t_id="394" sentence="17" number="393">defaulting</token>
<token t_id="395" sentence="17" number="394">.</token>
<token t_id="396" sentence="18" number="395">If</token>
<token t_id="397" sentence="18" number="396">too</token>
<token t_id="398" sentence="18" number="397">many</token>
<token t_id="399" sentence="18" number="398">of</token>
<token t_id="400" sentence="18" number="399">these</token>
<token t_id="401" sentence="18" number="400">lenders</token>
<token t_id="402" sentence="18" number="401">default</token>
<token t_id="403" sentence="18" number="402">,</token>
<token t_id="404" sentence="18" number="403">as</token>
<token t_id="405" sentence="18" number="404">it</token>
<token t_id="406" sentence="18" number="405">is</token>
<token t_id="407" sentence="18" number="406">feared</token>
<token t_id="408" sentence="18" number="407">may</token>
<token t_id="409" sentence="18" number="408">be</token>
<token t_id="410" sentence="18" number="409">happening</token>
<token t_id="411" sentence="18" number="410">now</token>
<token t_id="412" sentence="18" number="411">,</token>
<token t_id="413" sentence="18" number="412">the</token>
<token t_id="414" sentence="18" number="413">defaults</token>
<token t_id="415" sentence="18" number="414">can</token>
<token t_id="416" sentence="18" number="415">cascade</token>
<token t_id="417" sentence="18" number="416">upward</token>
<token t_id="418" sentence="18" number="417">.</token>
<token t_id="419" sentence="19" number="418">While</token>
<token t_id="420" sentence="19" number="419">no</token>
<token t_id="421" sentence="19" number="420">one</token>
<token t_id="422" sentence="19" number="421">is</token>
<token t_id="423" sentence="19" number="422">predicting</token>
<token t_id="424" sentence="19" number="423">major</token>
<token t_id="425" sentence="19" number="424">bank</token>
<token t_id="426" sentence="19" number="425">failures</token>
<token t_id="427" sentence="19" number="426">at</token>
<token t_id="428" sentence="19" number="427">this</token>
<token t_id="429" sentence="19" number="428">point</token>
<token t_id="430" sentence="19" number="429">,</token>
<token t_id="431" sentence="19" number="430">it</token>
<token t_id="432" sentence="19" number="431">is</token>
<token t_id="433" sentence="19" number="432">feared</token>
<token t_id="434" sentence="19" number="433">that</token>
<token t_id="435" sentence="19" number="434">their</token>
<token t_id="436" sentence="19" number="435">profits</token>
<token t_id="437" sentence="19" number="436">could</token>
<token t_id="438" sentence="19" number="437">be</token>
<token t_id="439" sentence="19" number="438">hurt</token>
<token t_id="440" sentence="19" number="439">.</token>


<Markables>
<ENTITY_MENTION m_id="27" syntactic_type="NAM" head="US" comment=""  >
<token_anchor t_id="107"/>
</ENTITY_MENTION>
<ENTITY_MENTION m_id="28" syntactic_type="NOM" head="stock exchanges" comment=""  >
<token_anchor t_id="38"/>
<token_anchor t_id="39"/>
<token_anchor t_id="40"/>
<token_anchor t_id="41"/>
<token_anchor t_id="42"/>
</ENTITY_MENTION>
<ENTITY_MENTION m_id="29" syntactic_type="NOM" head="globe" comment=""  >
<token_anchor t_id="41"/>
<token_anchor t_id="42"/>
</ENTITY_MENTION>
<ENTITY_MENTION m_id="30" syntactic_type="NOM" head="investors" comment=""  >
<token_anchor t_id="121"/>
</ENTITY_MENTION>
<ENTITY_MENTION m_id="104" head="" syntactic_type="" comment=""  >
<token_anchor t_id="25"/>
</ENTITY_MENTION>
<ENTITY_MENTION m_id="105" head="" syntactic_type="" comment=""  >
<token_anchor t_id="98"/>
<token_anchor t_id="99"/>
<token_anchor t_id="100"/>
<token_anchor t_id="101"/>
<token_anchor t_id="102"/>
<token_anchor t_id="103"/>
<token_anchor t_id="104"/>
<token_anchor t_id="105"/>
<token_anchor t_id="106"/>
<token_anchor t_id="107"/>
<token_anchor t_id="108"/>
</ENTITY_MENTION>
<ENTITY_MENTION m_id="1" syntactic_type="NOM" head="banks" comment=""  >
<token_anchor t_id="127"/>
<token_anchor t_id="128"/>
</ENTITY_MENTION>
<ENTITY_MENTION m_id="106" head="" syntactic_type="" comment=""  >
<token_anchor t_id="115"/>
<token_anchor t_id="116"/>
<token_anchor t_id="117"/>
<token_anchor t_id="118"/>
<token_anchor t_id="119"/>
</ENTITY_MENTION>
<ENTITY_MENTION m_id="2" syntactic_type="NAM" head="US" comment=""  >
<token_anchor t_id="127"/>
</ENTITY_MENTION>
<ENTITY_MENTION m_id="3" syntactic_type="NOM" head="banks" comment=""  >
<token_anchor t_id="131"/>
<token_anchor t_id="132"/>
<token_anchor t_id="133"/>
<token_anchor t_id="134"/>
<token_anchor t_id="135"/>
</ENTITY_MENTION>
<ENTITY_MENTION m_id="4" syntactic_type="NOM" head="globe" comment=""  >
<token_anchor t_id="134"/>
<token_anchor t_id="135"/>
</ENTITY_MENTION>
<ENTITY_MENTION m_id="5" syntactic_type="NOM" head="indices" comment=""  >
<token_anchor t_id="44"/>
<token_anchor t_id="45"/>
<token_anchor t_id="46"/>
<token_anchor t_id="47"/>
<token_anchor t_id="48"/>
<token_anchor t_id="49"/>
<token_anchor t_id="50"/>
</ENTITY_MENTION>
<ENTITY_MENTION m_id="6" syntactic_type="NAM" head="US" comment=""  >
<token_anchor t_id="47"/>
</ENTITY_MENTION>
<ENTITY_MENTION m_id="7" syntactic_type="PRE.NOM" head="sub-prime" comment=""  >
<token_anchor t_id="1"/>
</ENTITY_MENTION>
<ENTITY_MENTION m_id="8" syntactic_type="PRE.NOM" head="mortgage" comment=""  >
<token_anchor t_id="27"/>
<token_anchor t_id="28"/>
</ENTITY_MENTION>
<ENTITY_MENTION m_id="9" syntactic_type="NOM" head="price" comment=""  >
<token_anchor t_id="58"/>
<token_anchor t_id="59"/>
</ENTITY_MENTION>
<ENTITY_MENTION m_id="10" syntactic_type="" head="" comment=""  >
<token_anchor t_id="127"/>
<token_anchor t_id="128"/>
<token_anchor t_id="129"/>
<token_anchor t_id="130"/>
<token_anchor t_id="131"/>
<token_anchor t_id="132"/>
<token_anchor t_id="133"/>
<token_anchor t_id="134"/>
<token_anchor t_id="135"/>
</ENTITY_MENTION>
<ENTITY_MENTION m_id="11" syntactic_type="NAM" head="FTSE 100" comment=""  >
<token_anchor t_id="68"/>
<token_anchor t_id="69"/>
<token_anchor t_id="70"/>
<token_anchor t_id="71"/>
</ENTITY_MENTION>
<ENTITY_MENTION m_id="12" syntactic_type="NOM" head="their" comment=""  >
<token_anchor t_id="115"/>
</ENTITY_MENTION>
<ENTITY_MENTION m_id="13" syntactic_type="NAM" head="CAC 40" comment=""  >
<token_anchor t_id="73"/>
<token_anchor t_id="74"/>
<token_anchor t_id="75"/>
<token_anchor t_id="76"/>
</ENTITY_MENTION>
<ENTITY_MENTION m_id="14" syntactic_type="NAM" head="DAX 30" comment=""  >
<token_anchor t_id="78"/>
<token_anchor t_id="79"/>
<token_anchor t_id="80"/>
<token_anchor t_id="81"/>
<token_anchor t_id="82"/>
</ENTITY_MENTION>
<ENTITY_MENTION m_id="15" syntactic_type="NOM" head="lenders" comment=""  >
<token_anchor t_id="1"/>
<token_anchor t_id="2"/>
</ENTITY_MENTION>
<ENTITY_MENTION m_id="16" syntactic_type="CONJ" head="" comment=""  >
<token_anchor t_id="68"/>
<token_anchor t_id="69"/>
<token_anchor t_id="70"/>
<token_anchor t_id="71"/>
<token_anchor t_id="72"/>
<token_anchor t_id="73"/>
<token_anchor t_id="74"/>
<token_anchor t_id="75"/>
<token_anchor t_id="76"/>
<token_anchor t_id="77"/>
<token_anchor t_id="78"/>
<token_anchor t_id="79"/>
<token_anchor t_id="80"/>
<token_anchor t_id="81"/>
<token_anchor t_id="82"/>
</ENTITY_MENTION>
<ENTITY_MENTION m_id="17" syntactic_type="NAM" head="London" comment=""  >
<token_anchor t_id="68"/>
</ENTITY_MENTION>
<ENTITY_MENTION m_id="18" syntactic_type="NAM" head="Paris" comment=""  >
<token_anchor t_id="73"/>
</ENTITY_MENTION>
<ENTITY_MENTION m_id="19" syntactic_type="NAM" head="Frankfurt" comment=""  >
<token_anchor t_id="78"/>
</ENTITY_MENTION>
<ENTITY_MENTION m_id="20" syntactic_type="NOM" head="markets" comment=""  >
<token_anchor t_id="6"/>
<token_anchor t_id="7"/>
</ENTITY_MENTION>
<ENTITY_MENTION m_id="21" syntactic_type="NAM" head="Mortgage Bankers Association" comment=""  >
<token_anchor t_id="92"/>
<token_anchor t_id="93"/>
<token_anchor t_id="94"/>
<token_anchor t_id="95"/>
</ENTITY_MENTION>
<ENTITY_MENTION m_id="22" syntactic_type="NAM" head="China" comment=""  >
<token_anchor t_id="16"/>
</ENTITY_MENTION>
<ENTITY_MENTION m_id="23" syntactic_type="NOM" head="markets" comment=""  >
<token_anchor t_id="18"/>
<token_anchor t_id="19"/>
</ENTITY_MENTION>
<ENTITY_MENTION m_id="24" syntactic_type="" head="" comment=""  >
<token_anchor t_id="101"/>
</ENTITY_MENTION>
<ENTITY_MENTION m_id="25" syntactic_type="NOM" head="lenders" comment=""  >
<token_anchor t_id="27"/>
<token_anchor t_id="28"/>
<token_anchor t_id="29"/>
<token_anchor t_id="30"/>
<token_anchor t_id="31"/>
<token_anchor t_id="32"/>
<token_anchor t_id="33"/>
</ENTITY_MENTION>
<ENTITY_MENTION m_id="26" syntactic_type="NAM" head="United States" comment=""  >
<token_anchor t_id="31"/>
<token_anchor t_id="32"/>
<token_anchor t_id="33"/>
</ENTITY_MENTION>
<EVENT_MENTION m_id="31" time="NON_FUTURE" aspect="" special_cases="NONE" certainty="CERTAIN" polarity="POS" tense="" modality="" pred="jitters" comment="" pos="NOUN"  >
<token_anchor t_id="36"/>
</EVENT_MENTION>
<EVENT_MENTION m_id="32" time="NON_FUTURE" aspect="NONE" special_cases="NONE" certainty="CERTAIN" polarity="POS" tense="PAST" modality="" pred="fall" comment="" pos="VERB"  >
<token_anchor t_id="52"/>
</EVENT_MENTION>
<EVENT_MENTION m_id="33" time="NON_FUTURE" aspect="NONE" special_cases="NONE" certainty="CERTAIN" polarity="POS" tense="PRESPART" modality="" pred="mark" comment="" pos="VERB"  >
<token_anchor t_id="61"/>
</EVENT_MENTION>
<EVENT_MENTION m_id="34" time="NON_FUTURE" aspect="" special_cases="NONE" certainty="CERTAIN" polarity="POS" tense="" modality="" pred="loss" comment="" pos="NOUN"  >
<token_anchor t_id="64"/>
</EVENT_MENTION>
<EVENT_MENTION m_id="35" time="FUTURE" aspect="" special_cases="NONE" certainty="POSSIBLE" polarity="POS" tense="" modality="" pred="exposure" comment="" pos="NOUN"  >
<token_anchor t_id="138"/>
</EVENT_MENTION>
<EVENT_MENTION m_id="36" time="NON_FUTURE" aspect="" special_cases="NONE" certainty="POSSIBLE" polarity="POS" tense="INFINITIVE" modality="could" pred="have" comment="" pos="VERB"  >
<token_anchor t_id="137"/>
</EVENT_MENTION>
<EVENT_MENTION m_id="37" time="NON_FUTURE" aspect="" special_cases="NONE" certainty="CERTAIN" polarity="POS" tense="" modality="" pred="" comment="" pos="NOUN"  >
<token_anchor t_id="99"/>
<token_anchor t_id="104"/>
</EVENT_MENTION>
<EVENT_MENTION m_id="38" time="NON_FUTURE" aspect="NONE" special_cases="NONE" certainty="CERTAIN" polarity="POS" tense="PRESENT" modality="" pred="send" comment="" pos="VERB"  >
<token_anchor t_id="3"/>
</EVENT_MENTION>
<EVENT_MENTION m_id="39" time="NON_FUTURE" aspect="" special_cases="NONE" certainty="CERTAIN" polarity="POS" tense="" modality="" pred="jitters" comment="" pos="NOUN"  >
<token_anchor t_id="4"/>
</EVENT_MENTION>
<EVENT_MENTION m_id="40" time="NON_FUTURE" aspect="NONE" special_cases="NONE" certainty="CERTAIN" polarity="POS" tense="PAST" modality="" pred="close down" comment="" pos="VERB"  >
<token_anchor t_id="84"/>
<token_anchor t_id="85"/>
</EVENT_MENTION>
<EVENT_MENTION m_id="41" time="NON_FUTURE" aspect="NONE" special_cases="NONE" certainty="CERTAIN" polarity="POS" tense="PAST" modality="" pred="report" comment="" pos="VERB"  >
<token_anchor t_id="96"/>
</EVENT_MENTION>
<EVENT_MENTION m_id="42" time="NON_FUTURE" aspect="" special_cases="NONE" certainty="CERTAIN" polarity="POS" tense="" modality="" pred="payment" comment="" pos="NOUN"  >
<token_anchor t_id="99"/>
</EVENT_MENTION>
<EVENT_MENTION m_id="43" time="NON_FUTURE" aspect="" special_cases="NONE" certainty="CERTAIN" polarity="POS" tense="" modality="" pred="foreclosure" comment="" pos="NOUN"  >
<token_anchor t_id="104"/>
</EVENT_MENTION>
<EVENT_MENTION m_id="44" time="NON_FUTURE" aspect="NONE" special_cases="NONE" certainty="CERTAIN" polarity="POS" tense="PAST" modality="" pred="rise" comment="" pos="VERB"  >
<token_anchor t_id="109"/>
</EVENT_MENTION>
<EVENT_MENTION m_id="45" time="NON_FUTURE" aspect="NONE" special_cases="NONE" certainty="CERTAIN" polarity="POS" tense="PAST" modality="" pred="send" comment="" pos="VERB"  >
<token_anchor t_id="17"/>
</EVENT_MENTION>
<EVENT_MENTION m_id="46" time="NON_FUTURE" aspect="" special_cases="NONE" certainty="CERTAIN" polarity="POS" tense="" modality="" pred="tumble" comment="" pos="NOUN"  >
<token_anchor t_id="22"/>
</EVENT_MENTION>
<EVENT_MENTION m_id="47" time="NON_FUTURE" aspect="NONE" special_cases="NONE" certainty="CERTAIN" polarity="POS" tense="PRESPART" modality="" pred="grow" comment="" pos="VERB"  >
<token_anchor t_id="24"/>
</EVENT_MENTION>
<EVENT_MENTION m_id="48" time="NON_FUTURE" aspect="" special_cases="NONE" certainty="CERTAIN" polarity="POS" tense="" modality="" pred="worry" comment="" pos="NOUN"  >
<token_anchor t_id="25"/>
</EVENT_MENTION>
<EVENT_MENTION m_id="49" time="NON_FUTURE" aspect="NONE" special_cases="NONE" certainty="CERTAIN" polarity="POS" tense="PAST" modality="" pred="concerned" comment="" pos="OTHER"  >
<token_anchor t_id="123"/>
</EVENT_MENTION>
<EVENT_MENTION m_id="50" time="NON_FUTURE" aspect="PROGRESSIVE" special_cases="NONE" certainty="CERTAIN" polarity="POS" tense="PRESENT" modality="" pred="send" comment="" pos="VERB"  >
<token_anchor t_id="35"/>
</EVENT_MENTION>
<SIGNAL m_id="51" comment=""  >
<token_anchor t_id="55"/>
</SIGNAL>
<SIGNAL m_id="52" comment=""  >
<token_anchor t_id="65"/>
</SIGNAL>
<SIGNAL m_id="53" comment=""  >
<token_anchor t_id="15"/>
</SIGNAL>
<SIGNAL m_id="54" comment=""  >
<token_anchor t_id="118"/>
</SIGNAL>
<TIMEX3 m_id="59" functionInDocument="NONE" endPoint="" anchorTimeID="57" beginPoint="" value="2006-Q4" comment="" type="DATE"  >
<token_anchor t_id="111"/>
<token_anchor t_id="112"/>
<token_anchor t_id="113"/>
</TIMEX3>
<TIMEX3 m_id="60" functionInDocument="NONE" endPoint="" anchorTimeID="" beginPoint="" value="PXY" comment="" type="DURATION"  >
<token_anchor t_id="119"/>
</TIMEX3>
<TIMEX3 m_id="55" functionInDocument="NONE" endPoint="" anchorTimeID="57" beginPoint="" value="2007-03-12" comment="" type="DATE"  >
<token_anchor t_id="56"/>
</TIMEX3>
<TIMEX3 m_id="56" functionInDocument="NONE" endPoint="" anchorTimeID="" beginPoint="" value="2007" comment="" type="DATE"  >
<token_anchor t_id="66"/>
</TIMEX3>
<TIMEX3 m_id="57" functionInDocument="CREATION_TIME" endPoint="" anchorTimeID="" beginPoint="" value="2007-03-13" comment="" type="DATE"  >
<token_anchor t_id="8"/>
<token_anchor t_id="9"/>
<token_anchor t_id="10"/>
<token_anchor t_id="11"/>
</TIMEX3>
<TIMEX3 m_id="58" functionInDocument="NONE" endPoint="57" anchorTimeID="" beginPoint="83" value="P2W" comment="" type="DURATION"  >
<token_anchor t_id="13"/>
<token_anchor t_id="14"/>
</TIMEX3>
<VALUE m_id="61" type="PERCENT" comment=""  >
<token_anchor t_id="53"/>
<token_anchor t_id="54"/>
</VALUE>
<VALUE m_id="62" type="QUANTITY" comment=""  >
<token_anchor t_id="45"/>
</VALUE>
<VALUE m_id="63" type="PERCENT" comment=""  >
<token_anchor t_id="86"/>
<token_anchor t_id="87"/>
<token_anchor t_id="88"/>
<token_anchor t_id="89"/>
</VALUE>


<ENTITY m_id="64" RELATED_TO="" TAG_DESCRIPTOR="lenders" ent_type="PER" ent_class="GEN" comment="" external_ref="" />
<ENTITY m_id="65" RELATED_TO="" TAG_DESCRIPTOR="sub-prime mortgage" ent_type="FIN" ent_class="GEN" comment="" external_ref="" />
<ENTITY m_id="66" RELATED_TO="" TAG_DESCRIPTOR="global markets" ent_type="FIN" ent_class="GEN" comment="" external_ref="" />
<ENTITY m_id="67" RELATED_TO="" TAG_DESCRIPTOR="China" ent_type="LOC" ent_class="SPC" comment="" external_ref="" />
<ENTITY m_id="68" RELATED_TO="" TAG_DESCRIPTOR="United States" ent_type="LOC" ent_class="SPC" comment="" external_ref="" />
<ENTITY m_id="69" RELATED_TO="" TAG_DESCRIPTOR="globe" ent_type="LOC" ent_class="SPC" comment="" external_ref="" />
<ENTITY m_id="70" RELATED_TO="" TAG_DESCRIPTOR="three major indices" ent_type="FIN" ent_class="SPC" comment="" external_ref="" />
<ENTITY m_id="71" RELATED_TO="" TAG_DESCRIPTOR="price" ent_type="FIN" ent_class="SPC" comment="" external_ref="" />
<EVENT m_id="72" RELATED_TO="" TAG_DESCRIPTOR="send" class="OTHER" comment="" external_ref="" />
<EVENT m_id="73" RELATED_TO="" TAG_DESCRIPTOR="jitters" class="OTHER" comment="" external_ref="" />
<EVENT m_id="74" RELATED_TO="" TAG_DESCRIPTOR="send - china" class="OTHER" comment="" external_ref="" />
<EVENT m_id="75" RELATED_TO="" TAG_DESCRIPTOR="tumble" class="OTHER" comment="" external_ref="" />
<EVENT m_id="76" RELATED_TO="" TAG_DESCRIPTOR="grow" class="OTHER" comment="" external_ref="" />
<EVENT m_id="77" RELATED_TO="" TAG_DESCRIPTOR="worry" class="SPEECH_COGNITIVE" comment="" external_ref="" />
<EVENT m_id="78" RELATED_TO="" TAG_DESCRIPTOR="fall" class="OTHER" comment="" external_ref="" />
<EVENT m_id="79" RELATED_TO="" TAG_DESCRIPTOR="mark" class="OTHER" comment="" external_ref="" />
<EVENT m_id="80" RELATED_TO="" TAG_DESCRIPTOR="loss" class="OTHER" comment="" external_ref="" />
<EVENT m_id="81" RELATED_TO="" TAG_DESCRIPTOR="close down" class="OTHER" comment="" external_ref="" />
<EVENT m_id="82" RELATED_TO="" TAG_DESCRIPTOR="report" class="SPEECH_COGNITIVE" comment="" external_ref="" />
<TIMEX3 m_id="83" RELATED_TO="" TAG_DESCRIPTOR="2013-02-27" functionInDocument="NONE" endPoint="" anchorTimeID="" beginPoint="" value="2013-02-27" comment="" type="DATE" />
<ENTITY m_id="84" RELATED_TO="" TAG_DESCRIPTOR="London 's FTSE 100 , Paris ' CAC 40 and Frankfurt 's DAX 30 indices" ent_type="FIN" ent_class="SPC" comment="" external_ref="" />
<ENTITY m_id="85" RELATED_TO="" TAG_DESCRIPTOR="London" ent_type="LOC" ent_class="SPC" comment="" external_ref="" />
<ENTITY m_id="86" RELATED_TO="" TAG_DESCRIPTOR="Frankfurt" ent_type="LOC" ent_class="SPC" comment="" external_ref="" />
<ENTITY m_id="87" RELATED_TO="" TAG_DESCRIPTOR="Paris" ent_type="LOC" ent_class="SPC" comment="" external_ref="" />
<ENTITY m_id="88" RELATED_TO="" TAG_DESCRIPTOR="FTSE 100" ent_type="FIN" ent_class="SPC" comment="" external_ref="" />
<ENTITY m_id="89" RELATED_TO="" TAG_DESCRIPTOR="CAC 40" ent_type="FIN" ent_class="SPC" comment="" external_ref="" />
<ENTITY m_id="90" RELATED_TO="" TAG_DESCRIPTOR="DAX 30" ent_type="FIN" ent_class="SPC" comment="" external_ref="" />
<ENTITY m_id="91" RELATED_TO="" TAG_DESCRIPTOR="Mortgage Bankers Association" ent_type="ORG" ent_class="SPC" comment="" external_ref="" />
<ENTITY m_id="92" RELATED_TO="" TAG_DESCRIPTOR="investors" ent_type="PER" ent_class="GEN" comment="" external_ref="" />
<ENTITY m_id="93" RELATED_TO="" TAG_DESCRIPTOR="banks" ent_type="FIN" ent_class="GEN" comment="" external_ref="" />
<EVENT m_id="94" RELATED_TO="" TAG_DESCRIPTOR="payments and foreclosures" class="OTHER" comment="" external_ref="" />
<EVENT m_id="95" RELATED_TO="" TAG_DESCRIPTOR="payment" class="OTHER" comment="" external_ref="" />
<EVENT m_id="96" RELATED_TO="" TAG_DESCRIPTOR="foreclosure" class="OTHER" comment="" external_ref="" />
<EVENT m_id="97" RELATED_TO="" TAG_DESCRIPTOR="rise" class="OTHER" comment="" external_ref="" />
<EVENT m_id="98" RELATED_TO="" TAG_DESCRIPTOR="concerned" class="SPEECH_COGNITIVE" comment="" external_ref="" />
<ENTITY m_id="99" RELATED_TO="" TAG_DESCRIPTOR="multi-national banks" ent_type="FIN" ent_class="GEN" comment="" external_ref="" />
<EVENT m_id="100" RELATED_TO="" TAG_DESCRIPTOR="have" class="GRAMMATICAL" comment="" external_ref="" />
<EVENT m_id="101" RELATED_TO="" TAG_DESCRIPTOR="exposure" class="OTHER" comment="" external_ref="" />
<ENTITY m_id="102" RELATED_TO="" TAG_DESCRIPTOR="US banks but also multi-national banks around the globe" ent_type="FIN" ent_class="GEN" comment="" external_ref="" />
<ENTITY m_id="103" RELATED_TO="" TAG_DESCRIPTOR="mortgage" ent_type="FIN" ent_class="GEN" comment="" external_ref="" />
</Markables>

<Relations>
<GLINK r_id="485277" >
<source m_id="41" />
<target m_id="44" />
</GLINK>
<TLINK r_id="485278" reltype="BEFORE" comment="" signalID="" >
<source m_id="45" />
<target m_id="50" />
</TLINK>
<TLINK r_id="485279" reltype="SIMULTANEOUS" comment="" signalID="" >
<source m_id="32" />
<target m_id="40" />
</TLINK>
<TLINK r_id="485280" reltype="BEFORE" comment="" signalID="" >
<source m_id="45" />
<target m_id="32" />
</TLINK>
<TLINK r_id="485281" reltype="INCLUDES" comment="" signalID="" >
<source m_id="57" />
<target m_id="41" />
</TLINK>
<TLINK r_id="485282" reltype="INCLUDES" comment="" signalID="" >
<source m_id="57" />
<target m_id="40" />
</TLINK>
<TLINK r_id="485283" reltype="IS_INCLUDED" comment="" signalID="52" >
<source m_id="34" />
<target m_id="56" />
</TLINK>
<TLINK r_id="485284" reltype="AFTER" comment="" signalID="51" >
<source m_id="32" />
<target m_id="55" />
</TLINK>
<TLINK r_id="485285" reltype="AFTER" comment="" signalID="" >
<source m_id="57" />
<target m_id="45" />
</TLINK>
<TLINK r_id="485286" reltype="INCLUDES" comment="" signalID="" >
<source m_id="57" />
<target m_id="32" />
</TLINK>
<TLINK r_id="485287" reltype="AFTER" comment="" signalID="" >
<source m_id="41" />
<target m_id="44" />
</TLINK>
<TLINK r_id="485288" reltype="IS_INCLUDED" comment="" signalID="" >
<source m_id="44" />
<target m_id="59" />
</TLINK>
<TLINK r_id="485289" reltype="AFTER" comment="" signalID="" >
<source m_id="40" />
<target m_id="41" />
</TLINK>
<HAS_PARTICIPANT r_id="485290" frame="" sem_role_framework="PROPBANK" sem_role="Arg0" eso_class="" eso_role="" comment="" frame_element="" >
<source m_id="38" />
<target m_id="15" />
</HAS_PARTICIPANT>
<HAS_PARTICIPANT r_id="485291" frame="" sem_role_framework="PROPBANK" sem_role="Arg1" eso_class="" eso_role="" comment="" frame_element="" >
<source m_id="45" />
<target m_id="23" />
</HAS_PARTICIPANT>
<HAS_PARTICIPANT r_id="485292" frame="" sem_role_framework="PROPBANK" sem_role="Arg0" eso_class="" eso_role="" comment="" frame_element="" >
<source m_id="45" />
<target m_id="22" />
</HAS_PARTICIPANT>
<HAS_PARTICIPANT r_id="485293" frame="" sem_role_framework="PROPBANK" sem_role="Arg1" eso_class="" eso_role="" comment="" frame_element="" >
<source m_id="48" />
<target m_id="25" />
</HAS_PARTICIPANT>
<HAS_PARTICIPANT r_id="485294" frame="" sem_role_framework="PROPBANK" sem_role="Arg0" eso_class="" eso_role="" comment="" frame_element="" >
<source m_id="50" />
<target m_id="25" />
</HAS_PARTICIPANT>
<HAS_PARTICIPANT r_id="485295" frame="" sem_role_framework="PROPBANK" sem_role="Argm-OTHER" eso_class="" eso_role="" comment="" frame_element="" >
<source m_id="39" />
<target m_id="20" />
</HAS_PARTICIPANT>
<HAS_PARTICIPANT r_id="485296" frame="" sem_role_framework="PROPBANK" sem_role="Argm-OTHER" eso_class="" eso_role="" comment="" frame_element="" >
<source m_id="31" />
<target m_id="28" />
</HAS_PARTICIPANT>
<HAS_PARTICIPANT r_id="485297" frame="" sem_role_framework="PROPBANK" sem_role="Arg1" eso_class="Decreasing" eso_role="quantity-item" comment="" frame_element="" >
<source m_id="32" />
<target m_id="5" />
</HAS_PARTICIPANT>
<HAS_PARTICIPANT r_id="485298" frame="" sem_role_framework="PROPBANK" sem_role="Arg2" eso_class="Decreasing" eso_role="quantity-ratio" comment="" frame_element="" >
<source m_id="32" />
<target m_id="61" />
</HAS_PARTICIPANT>
<HAS_PARTICIPANT r_id="485299" frame="" sem_role_framework="PROPBANK" sem_role="Arg2" eso_class="" eso_role="" comment="" frame_element="" >
<source m_id="40" />
<target m_id="63" />
</HAS_PARTICIPANT>
<HAS_PARTICIPANT r_id="485300" frame="" sem_role_framework="PROPBANK" sem_role="Arg1" eso_class="" eso_role="" comment="" frame_element="" >
<source m_id="40" />
<target m_id="16" />
</HAS_PARTICIPANT>
<HAS_PARTICIPANT r_id="485301" frame="" sem_role_framework="PROPBANK" sem_role="Arg0" eso_class="" eso_role="" comment="" frame_element="" >
<source m_id="41" />
<target m_id="21" />
</HAS_PARTICIPANT>
<HAS_PARTICIPANT r_id="485302" frame="" sem_role_framework="PROPBANK" sem_role="Argm-LOC" eso_class="" eso_role="" comment="" frame_element="" >
<source m_id="43" />
<target m_id="27" />
</HAS_PARTICIPANT>
<HAS_PARTICIPANT r_id="485303" frame="" sem_role_framework="PROPBANK" sem_role="Arg3" eso_class="Paying" eso_role="possession-theme" comment="" frame_element="" >
<source m_id="42" />
<target m_id="24" />
</HAS_PARTICIPANT>
<HAS_PARTICIPANT r_id="485304" frame="" sem_role_framework="PROPBANK" sem_role="Arg1" eso_class="" eso_role="" comment="" frame_element="" >
<source m_id="49" />
<target m_id="30" />
</HAS_PARTICIPANT>
<HAS_PARTICIPANT r_id="485305" frame="" sem_role_framework="PROPBANK" sem_role="Arg0" eso_class="" eso_role="" comment="" frame_element="" >
<source m_id="36" />
<target m_id="10" />
</HAS_PARTICIPANT>
<REFERS_TO r_id="485306" >
<source m_id="7" />
<source m_id="8" />
<target m_id="65" />
</REFERS_TO>
<REFERS_TO r_id="485307" >
<source m_id="20" />
<source m_id="23" />
<source m_id="28" />
<target m_id="66" />
</REFERS_TO>
<REFERS_TO r_id="485308" >
<source m_id="22" />
<target m_id="67" />
</REFERS_TO>
<REFERS_TO r_id="485309" >
<source m_id="2" />
<source m_id="6" />
<source m_id="26" />
<source m_id="27" />
<target m_id="68" />
</REFERS_TO>
<REFERS_TO r_id="485310" >
<source m_id="4" />
<source m_id="29" />
<target m_id="69" />
</REFERS_TO>
<REFERS_TO r_id="485311" >
<source m_id="5" />
<target m_id="70" />
</REFERS_TO>
<REFERS_TO r_id="485312" >
<source m_id="9" />
<target m_id="71" />
</REFERS_TO>
<REFERS_TO r_id="485313" >
<source m_id="38" />
<source m_id="50" />
<target m_id="72" />
</REFERS_TO>
<REFERS_TO r_id="485314" >
<source m_id="17" />
<target m_id="85" />
</REFERS_TO>
<REFERS_TO r_id="485315" >
<source m_id="19" />
<target m_id="86" />
</REFERS_TO>
<REFERS_TO r_id="485316" >
<source m_id="12" />
<source m_id="16" />
<target m_id="84" />
</REFERS_TO>
<REFERS_TO r_id="485317" >
<source m_id="13" />
<target m_id="89" />
</REFERS_TO>
<REFERS_TO r_id="485318" >
<source m_id="14" />
<target m_id="90" />
</REFERS_TO>
<REFERS_TO r_id="485319" >
<source m_id="18" />
<target m_id="87" />
</REFERS_TO>
<REFERS_TO r_id="485320" >
<source m_id="11" />
<target m_id="88" />
</REFERS_TO>
<REFERS_TO r_id="485321" >
<source m_id="10" />
<target m_id="102" />
</REFERS_TO>
<REFERS_TO r_id="485322" >
<source m_id="44" />
<target m_id="97" />
</REFERS_TO>
<REFERS_TO r_id="485323" >
<source m_id="31" />
<source m_id="39" />
<target m_id="73" />
</REFERS_TO>
<REFERS_TO r_id="485324" >
<source m_id="41" />
<target m_id="82" />
</REFERS_TO>
<REFERS_TO r_id="485325" >
<source m_id="40" />
<target m_id="81" />
</REFERS_TO>
<REFERS_TO r_id="485326" >
<source m_id="34" />
<target m_id="80" />
</REFERS_TO>
<REFERS_TO r_id="485327" >
<source m_id="33" />
<target m_id="79" />
</REFERS_TO>
<REFERS_TO r_id="485328" >
<source m_id="32" />
<target m_id="78" />
</REFERS_TO>
<REFERS_TO r_id="485329" >
<source m_id="48" />
<target m_id="77" />
</REFERS_TO>
<REFERS_TO r_id="485330" >
<source m_id="47" />
<target m_id="76" />
</REFERS_TO>
<REFERS_TO r_id="485331" >
<source m_id="46" />
<target m_id="75" />
</REFERS_TO>
<REFERS_TO r_id="485332" >
<source m_id="1" />
<target m_id="93" />
</REFERS_TO>
<REFERS_TO r_id="485333" >
<source m_id="42" />
<target m_id="95" />
</REFERS_TO>
<REFERS_TO r_id="485334" >
<source m_id="37" />
<target m_id="94" />
</REFERS_TO>
<REFERS_TO r_id="485335" >
<source m_id="45" />
<target m_id="74" />
</REFERS_TO>
<REFERS_TO r_id="485336" >
<source m_id="43" />
<target m_id="96" />
</REFERS_TO>
<REFERS_TO r_id="485337" >
<source m_id="3" />
<target m_id="99" />
</REFERS_TO>
<REFERS_TO r_id="485338" >
<source m_id="49" />
<target m_id="98" />
</REFERS_TO>
<REFERS_TO r_id="485339" >
<source m_id="35" />
<target m_id="101" />
</REFERS_TO>
<REFERS_TO r_id="485340" >
<source m_id="15" />
<source m_id="25" />
<target m_id="64" />
</REFERS_TO>
<REFERS_TO r_id="485341" >
<source m_id="36" />
<target m_id="100" />
</REFERS_TO>
<REFERS_TO r_id="485342" >
<source m_id="21" />
<target m_id="91" />
</REFERS_TO>
<REFERS_TO r_id="485343" >
<source m_id="30" />
<target m_id="92" />
</REFERS_TO>
<REFERS_TO r_id="485344" >
<source m_id="24" />
<target m_id="103" />
</REFERS_TO>
<HAS_PARTICIPANT r_id="494954" frame="" sem_role_framework="PROPBANK" sem_role="Arg0" eso_class="Decreasing" eso_role="" comment="" frame_element="" >
<source m_id="46" />
</HAS_PARTICIPANT>
<HAS_PARTICIPANT r_id="494955" frame="" sem_role_framework="PROPBANK" sem_role="Arg0" eso_class="Increasing" eso_role="quantity-item" comment="" frame_element="" >
<source m_id="47" />
<target m_id="25" />
</HAS_PARTICIPANT>
<HAS_PARTICIPANT r_id="494956" frame="" sem_role_framework="PROPBANK" sem_role="Arg0" eso_class="Increasing" eso_role="quantity-attribute" comment="" frame_element="" >
<source m_id="47" />
<target m_id="104" />
</HAS_PARTICIPANT>
<HAS_PARTICIPANT r_id="494957" frame="" sem_role_framework="PROPBANK" sem_role="Arg0" eso_class="Increasing" eso_role="quantity-item" comment="" frame_element="" >
<source m_id="44" />
<target m_id="105" />
</HAS_PARTICIPANT>
<HAS_PARTICIPANT r_id="494958" frame="" sem_role_framework="PROPBANK" sem_role="Arg0" eso_class="Increasing" eso_role="quantity-value_2" comment="" frame_element="" >
<source m_id="44" />
<target m_id="106" />
</HAS_PARTICIPANT>
</Relations>
</Document>
